hello_felictte1963-0.1.0.dist-info/METADATA
hello_felictte1963-0.1.0.dist-info/WHEEL
hello_felictte1963/__init__.py
hello_felictte1963-0.1.0.dist-info/RECORD
