Metadata-Version: 2.1
Name: hello-felictte1963
Version: 0.1.0
Summary: Docker First Deployment
Author-Email: Felicette1963 <xorudlee4869@gmail.com>
License: MIT
Requires-Python: >=3.8
